{"o":"Comune di Pegognaga","fc":"00217110204","s":[{"i":"01EZ4TPE95EZPPHZMZ7DFFHTZK","n":"PAGAMENTI SERVIZI SCOLASTICI","d":"<p>Il servizio di Pagamenti per i servizi scolastici offre la possibilità di gestire dei pagamenti direttamente attraverso l’app, oltre alle normali modalità di pagamento già previste.<br />\nTramite IO potrai ricevere avvisi per:</p>\n\n<ul>\n  <li>pagamento della mensa scolastica</li>\n  <li>pagamento del trasporto scolastico</li>\n  <li>pagamento del pre scuola.</li>\n</ul>\n","sc":"LOCAL","q":1}],"prefix":"Comune di ","fn":"Pegognaga","st":"PEGOGNAGA"}