{"o":"Comune di Melito di Porto Salvo","fc":"00281270801","s":[{"i":"01F12EESVZVZH3ESW9NTFKW7GZ","n":"Ufficio Anagrafe","d":"<p>In questa sezione potrai trovare gli avvisi di pagamento relativi a questo servizio</p>\n","sc":"LOCAL","q":1},{"i":"01F12EFGV6YCZDCKABN3GVQMNM","n":"Diritti Di Segreteria Ufficio Tecnico","d":"<p>In questa sezione potrai trovare gli avvisi di pagamento relativi a questo servizio</p>\n","sc":"LOCAL","q":1},{"i":"01F12EWJBMWVKSKRV7REB982DA","n":"Diritti Di Sgreteria","d":"<p>In questa sezione potrai trovare gli avvisi di pagamento relativi a questo servizio</p>\n","sc":"LOCAL","q":1},{"i":"01F1MYGN5TKGDQ5A32R9V2HHGG","n":"Tari","d":"<p>In questa sezione potrai trovare gli avvisi di pagamento relativi a questo servizio</p>\n","sc":"LOCAL","q":1},{"i":"01F1N07FZF9D10WTFYB5N00EXJ","n":"Canone Occupazione Suolo Aree Pubbliche","d":"<p>In questa sezione potrai trovare gli avvisi di pagamento relativi a questo servizio</p>\n","sc":"LOCAL","q":1},{"i":"01F1N07KRXSAE5EZ25X3RDHW5X","n":"Imposta Comunale Pubblicita'","d":"<p>In questa sezione potrai trovare gli avvisi di pagamento relativi a questo servizio</p>\n","sc":"LOCAL","q":1},{"i":"01F1MZB1BYEMT52945HS6Y35C2","n":"Servizio Idrico","d":"<p>In questa sezione potrai trovare gli avvisi di pagamento relativi a questo servizio</p>\n","sc":"LOCAL","q":1},{"i":"01F12EQXV8MPGWV8BK2FCQ4TB1","n":"Sportello Attivita' Produttive","d":"<p>In questa sezione potrai trovare gli avvisi di pagamento relativi a questo servizio</p>\n","sc":"LOCAL","q":1},{"i":"01F1MZB4T44JKBB03GZWD5BJ97","n":"Avvisi Osl","d":"<p>In questa sezione potrai trovare gli avvisi di pagamento relativi a questo servizio</p>\n","sc":"LOCAL","q":1},{"i":"01F12ETZPJ3CAWRZD129C674WA","n":"Polizia Locale","d":"<p>In questa sezione potrai trovare gli avvisi di pagamento relativi a questo servizio</p>\n","sc":"LOCAL","q":1},{"i":"01F0X6ZVRT9K85K0W0S04AMVVM","n":"Servizi Scolastici","d":"<p>In questa sezione potrai trovare gli avvisi di pagamento relativi a questo servizio</p>\n","sc":"LOCAL","q":1},{"i":"01F12EK4920ZPXB0XG93VEZ953","n":"Polizia Mortuaria","d":"<p>In questa sezione potrai trovare gli avvisi di pagamento relativi a questo servizio</p>\n","sc":"LOCAL","q":1},{"i":"01F12ENKBRYG6828H5W8TP2QVT","n":"Fitti Sale E Aree Comunali","d":"<p>In questa sezione potrai trovare gli avvisi di pagamento relativi a questo servizio</p>\n","sc":"LOCAL","q":1},{"i":"01F12EREZ3XPFHEH81WXEN25EC","n":"Servizi Cimiteriali","d":"<p>In questa sezione potrai trovare gli avvisi di pagamento relativi a questo servizio</p>\n","sc":"LOCAL","q":1},{"i":"01F1MZB8G3YC8E6MKKB8ZBFYGK","n":"Fatture Osl","d":"<p>In questa sezione potrai trovare gli avvisi di pagamento relativi a questo servizio</p>\n","sc":"LOCAL","q":1}],"prefix":"Comune di ","fn":"Melito di Porto Salvo","st":"MELITO DI PORTO SALVO"}