{"fc":"00311560361","o":"Comune di San Cesario sul Panaro","s":[{"d":"<p>In questa sezione potrai trovare gli avvisi di pagamento relativi a questo servizio.</p>\n","i":"01EYZJ86QFT7GPP6H1Q457ATVR","n":"Lavori Pubblici Tecnico Manutentivo","q":1,"sc":"LOCAL"},{"d":"<p>In questa sezione potrai trovare gli avvisi di pagamento relativi a questo servizio.</p>\n","i":"01EYZJ80BJFG2GXCM6AQ7QNQ0Z","n":"Urbanistica - Edilizia Privata - Ambiente","q":1,"sc":"LOCAL"},{"d":"<p>In questa sezione potrai trovare gli avvisi di pagamento relativi a questo servizio.</p>\n","i":"01EYZJ82K9XMECBYV42V85D4A3","n":"Polizia Municipale","q":1,"sc":"LOCAL"},{"d":"<p>In questa sezione potrai trovare gli avvisi di pagamento relativi a questo servizio.</p>\n","i":"01EYZJ88S82WRWQJNBA2ACVNGB","n":"Servizi Scolastici","q":1,"sc":"LOCAL"},{"d":"<p>In questa sezione potrai trovare gli avvisi di pagamento relativi a questo servizio.</p>\n","i":"01EYZJ7Y7DPC7WDZZA1084791V","n":"Affari Istituzionali","q":1,"sc":"LOCAL"},{"d":"<p>In questa sezione potrai trovare gli avvisi di pagamento relativi a questo servizio.</p>\n","i":"01EYZJ84NY4QB76PEBWW3SNSRC","n":"Servizio Finanziario","q":1,"sc":"LOCAL"}],"prefix":"Comune di ","fn":"San Cesario sul Panaro","st":"SAN CESARIO SUL PANARO"}