{"o":"Comune di Careggine","fc":"00398730465","s":[{"i":"01F03H3ZPA7YGHMEWSAX4KM64K","n":"Comunicazioni Istituzionali","d":"<p>“Il servizio comunicazioni istituzionali ti informa sulle attività dell’Ente che ti riguardano.</p>\n\n<p>Tramite App IO potrai:</p>\n<ul>\n  <li>ricevere comunicazioni di carattere generale dagli uffici dell’Ente</li>\n  <li>ricevere comunicazioni inerenti sedute di Giunta e Consiglio</li>\n  <li>ricevere comunicazioni inerenti sedute di Commissioni”</li>\n</ul>\n","sc":"LOCAL","q":0}],"prefix":"Comune di ","fn":"Careggine","st":"CAREGGINE"}