{"o":"Comune di Villa Minozzo","fc":"00431620350","s":[{"i":"01EZF3KRWF1XYDXNS3GR4A2TZE","n":"Ufficio Commercio Pubblicita'  E Cosap","d":"<p>In questa sezione potrai trovare gli avvisi di pagamento relativi a questo servizio.</p>\n","sc":"LOCAL","q":1},{"i":"01EZF3HSK68S7Z1T544P7WAX6A","n":"Diritti Di Segreteria","d":"<p>In questa sezione potrai trovare gli avvisi di pagamento relativi a questo servizio.</p>\n","sc":"LOCAL","q":1},{"i":"01EZF3J28P99YZ811BGYPVVJ5B","n":"Ufficio Anagrafe","d":"<p>In questa sezione potrai trovare gli avvisi di pagamento relativi a questo servizio.</p>\n","sc":"LOCAL","q":1},{"i":"01EZF3M91CZV16XYN477S91CX3","n":"Ufficio Tecnico","d":"<p>In questa sezione potrai trovare gli avvisi di pagamento relativi a questo servizio.</p>\n","sc":"LOCAL","q":1},{"i":"01EZF3N99XQQGNGYE9MCCZQDK9","n":"Servizi Cimiteriali","d":"<p>In questa sezione potrai trovare gli avvisi di pagamento relativi a questo servizio.</p>\n","sc":"LOCAL","q":1},{"i":"01EZF3RA27AEP2JY5DQCJR6T1N","n":"Stato Civile","d":"<p>In questa sezione potrai trovare gli avvisi di pagamento relativi a questo servizio.</p>\n","sc":"LOCAL","q":1}],"prefix":"Comune di ","fn":"Villa Minozzo","st":"VILLA MINOZZO"}