{"fc":"00452370067","o":"Comune di Frassinello Monferrato","s":[{"d":"<p>“Il servizio di Avviso scadenza carta d’identità permette di essere informati relativamente alla scadenza del proprio documento di identità. \nTramite IO potrai:</p>\n\n<ul>\n  <li>ricevere una notifica in prossimità della data di scadenza della tua carta d’identità.”</li>\n</ul>\n","i":"01EYR9EADS7FRB60V812P7TMGE","n":"AVVISO SCADENZA CARTA D'IDENTITA'","q":1,"sc":"LOCAL"}],"prefix":"Comune di ","fn":"Frassinello Monferrato","st":"FRASSINELLO MONFERRATO"}