{"fc":"00460930365","o":"Comune di Lama Mocogno","s":[{"d":"<p>Tramite Io  potrai ricevere comunicazioni  relative a  alla scadenza della carta d’identità</p>\n","i":"01FPYQFD88D62RX7TT0A5ZZAEA","n":"Comunicazioni relative alla scadenza della carta d'identità","q":1,"sc":"LOCAL"},{"d":"<p>Tramite IO potrai ricevere le notifiche e gli avvisi di pagamento relativi al servizio centro estivo</p>\n","i":"01FPYTNMQ3MVH6D448SD3VJY3M","n":"Servizio Centri estivo","q":1,"sc":"LOCAL"},{"d":"<p>Tramite IO potrai ricevere le notifiche e gli avvisi di pagamento relativi al Canone unico</p>\n","i":"01FPYRG52YFRZSC47GF76EF6H3","n":"Canone Unico ","q":1,"sc":"LOCAL"},{"d":"<p>Tramite app IO  potrai ricevere comunicazioni  relative alla Tassa sui rifiuti.</p>\n","i":"01FPYVEF31DHPZH6NPDQ3WAM7V","n":"Comunicazioni relative alla tassa sui rifiuti","q":1,"sc":"LOCAL"},{"d":"<p>Tramite IO potrai ricevere le notifiche e gli avvisi di pagamento relativi al Servizio di pre e post scuola</p>\n","i":"01FPZ8KM3RQARY2TT372HPHNAT","n":"Servizio di pre e post scuola","q":1,"sc":"LOCAL"},{"d":"<p>Tramite IO potrai ricevere le notifiche e gli avvisi di pagamento relativi al Servizio di trasporto scolastico</p>\n","i":"01FPZ8ZZMRGSR2ARM4FZDH8PNK","n":"Servizio Trasporto scolastico","q":1,"sc":"LOCAL"},{"d":"<p>Tramite IO potrai ricevere le notifiche e gli avvisi di pagamento relativi al Servizio di gestione dell’Illuminazione Votiva</p>\n","i":"01FPZA5WE9284Q2DWF237TYNPK","n":"Servizio Illuminazione Votiva","q":1,"sc":"LOCAL"},{"d":"<p>Tramite IO potrai ricevere le notifiche e gli avvisi di pagamento relativi al Servizio  Piccolo Gruppo Educativo Lo Scoiattolo.</p>\n","i":"01FPZ83SGPRHHFMK3HXCNQ261K","n":"Servizio Piccolo Gruppo Educativo Lo Scoiattolo","q":1,"sc":"LOCAL"},{"d":"<p>Tramite IO potrai ricevere le notifiche e gli avvisi di pagamento relativi al Servizio di mensa scolastica</p>\n","i":"01FPYVTY1MCDKDKWW7K3WQAY2J","n":"Servizio di mensa scolastica","q":1,"sc":"LOCAL"},{"d":"<p>Tramite app IO  potrai ricevere comunicazioni  relative ai tesserini per parcheggio per disabili</p>\n","i":"01FPYWE2E213WZFAZRBEJFJAYE","n":"Comunicazioni relative ai tesserini per parcheggio per disabili","q":1,"sc":"LOCAL"},{"d":"<p>Tramite IO potrai ricevere le notifiche e gli avvisi di pagamento relativi al Canone unico mercatale</p>\n","i":"01FPYPKKQBCADA6HFM01VHBHFV","n":"Canone Unico Mercatale","q":1,"sc":"LOCAL"},{"d":"<p>Tramite app IO  potrai trovare ricevere comunicazioni  relative all’IMU</p>\n","i":"01FPYV6G2C7XB0VFZ3HJC3C57P","n":"Comunicazioni relative all'Imposta municipale Unica  (IMU)","q":1,"sc":"LOCAL"}],"prefix":"Comune di ","fn":"Lama Mocogno","st":"LAMA MOCOGNO"}