{"o":"Comune di Bornasco","fc":"00520620188","s":[{"i":"01FA371M7ZGCFMJ7C1P35VR4S9","n":"POST SCUOLA","d":"<p>servizio di post scuola per alunni</p>\n","sc":"LOCAL","q":1},{"i":"01FA375A7RS6FR62XYWFHPJ9QZ","n":"AFFITTO SALA POLIFUNZIONALE DI BORNASCO","d":"<p>affitto locali polifunzionali comunali</p>\n","sc":"LOCAL","q":1},{"i":"01FA375VA20H5KMEHAZHCKXWC7","n":"AFFITTO SALA POLIFUNZIONALE DI GUALDRASCO","d":"<p>affitto locale polifunzionale comunali</p>\n","sc":"LOCAL","q":1},{"i":"01FA37AJP9YQSZJNCD1TXFNKB9","n":"CONCESSIONI CIMITERIALI","d":"<p>concessioni cimiteriali</p>\n","sc":"LOCAL","q":1},{"i":"01FA37BG7X2ANZTXP2GRKPYXDG","n":"DIRITTI DI SEGRETERIA UFFICIO TECNICO","d":"<p>DIRITTI DI SEGRETERIA UFFICIO TECNICO</p>\n","sc":"LOCAL","q":1},{"i":"01FA371XY580HW4AS0PY7KBD2T","n":"LABORATORI COMUNALI","d":"<p>SERVIZIO POMERIGGI INTEGRATIVI PER ALUNNI</p>\n","sc":"LOCAL","q":1},{"i":"01EXPQEM2R705WQGAK0Y2KVV7R","n":"Carta d'identità elettronica","d":"<p>Il servizio CIE include l’emissione della carta di identità elettronica per scadenza naturale della carta di identità precedente o per smarrimento o furto della carta di identità.<br />\nTramite IO potrai:</p>\n\n<ul>\n  <li>procedere al pagamento della nuova CIE (carta di identità elettronica).</li>\n</ul>\n","sc":"LOCAL","q":1},{"i":"01F2TY0C7DSYEB68V2KP37632R","n":"REFEZIONE SCOLASTICA","d":"<p>SERVIZIO MENSA SCOLASTICA</p>\n","sc":"LOCAL","q":1},{"i":"01FA37C4CCC1FZB6VHC1DTXW34","n":"SANZIONI CODICE DELLA STRADA","d":"<p>MULTE E SANZIONI CODICE DELLA STRADA</p>\n","sc":"LOCAL","q":1},{"i":"01FA370YNRBZDEE7EEDHZ3J1JS","n":"TRASPORTO SCOLASTICO","d":"<p>SERVIZIO DI TRASPORTO SCOLASTICO PER ALUNNI</p>\n","sc":"LOCAL","q":1},{"i":"01FA371BVW6NJN3A174E1HYGSC","n":"PRE SCUOLA","d":"<p>servizio di pre scuola per alunni</p>\n","sc":"LOCAL","q":1}],"prefix":"Comune di ","fn":"Bornasco","st":"BORNASCO"}