{"o":"Ambiente Servizi S.p.a.","fc":"01434200935","s":[{"i":"01EV6JNRS1NHQYX6EPQNJFNKMZ","n":"Informazioni all'utenza","d":"<p>Il servizio viene utilizzato dall’ente per inviarti informazioni istituzionali.</p>\n","sc":"LOCAL","q":0},{"i":"01EV6JP8PY7K027KFCH7GC38R3","n":"Scadenza pagamento TARI","d":"<p>Il servizio viene utilizzato dall’azienda per informarti quando viene emesso un avviso di pagamento a te indirizzato. Il bacino di utenza servito dall’azienda è circoscritto \nai comuni serviti in provincia di Pordenone.</p>\n","sc":"LOCAL","q":0}],"prefix":null,"fn":"Ambiente Servizi S.p.a.","st":"AMBIENTE SERVIZI S.P.A."}