{"fc":"02641830589","o":"Comune di Ladispoli","s":[{"d":"<p>l servizio informa il cittadino, impresa, professionista circa il  passaggio ad una fase procedimentale successiva nell’ambito della gestione del procedimento amministrativo avviato da portale e trasmesso per via telematica. Tramite IO potrai:</p>\n\n<p>-ricevere avvisi sul cambio di stato di una pratica</p>\n","i":"01EZ795XZB1PQY8QT4H92YJ2NK","n":"Servizio di cambio di stato","q":1,"sc":"LOCAL"}],"prefix":"Comune di ","fn":"Ladispoli","st":"LADISPOLI"}