{"o":"Comune di Mazzano Romano","fc":"03007620580","s":[{"i":"01EZ4VPBC69VVDT96YNJZHYHCJ","n":"Attività Produttive","d":"<p>In questa sezione potrai trovare gli avvisi di pagamento relativi a questo servizio.</p>\n","sc":"LOCAL","q":1},{"i":"01EZ4VQ9TKXWWBTFA30MJSP6ZM","n":"Servizio Idrico","d":"<p>In questa sezione potrai trovare gli avvisi di pagamento relativi a questo servizio.</p>\n","sc":"LOCAL","q":1},{"i":"01EZ4VPMCH3RKN4NTQ0FAX31RP","n":"Ufficio Tecnico","d":"<p>In questa sezione potrai trovare gli avvisi di pagamento relativi a questo servizio.</p>\n","sc":"LOCAL","q":1},{"i":"01EZ4VPXF8DT774ZG1WXQ97VRE","n":"Ufficio Tributi","d":"<p>In questa sezione potrai trovare gli avvisi di pagamento relativi a questo servizio.</p>\n","sc":"LOCAL","q":1},{"i":"01EZ4VQ30AD0Z2X2TG0X3ZM46H","n":"Area 1","d":"<p>In questa sezione potrai trovare gli avvisi di pagamento relativi a questo servizio.</p>\n","sc":"LOCAL","q":1}],"prefix":"Comune di ","fn":"Mazzano Romano","st":"MAZZANO ROMANO"}