{"fc":"05841790826","o":"Azienda Ospedaliera Universitaria Policlinico P. Giaccone","s":[{"d":"<p>Tramite io potrai ricevere tutte le informazioni utili relative alla tua prenotazione in regime SSN o ALP comprese quelle relative al pagamento tramite circuito PagoPA</p>\n","i":"01FCNG7KQTG0FXR9BZDNQ2JBFQ","n":"Servizio di prenotazione di prestazioni assistenziali in regime SSN e ALP","q":1,"sc":"LOCAL"}],"prefix":null,"fn":"Azienda Ospedaliera Universitaria Policlinico P. Giaccone","st":"AZIENDA OSPEDALIERA UNIVERSITARIA POLICLINICO P. GIACCONE"}