{"fc":"08496131213","o":"Acer Campania","s":[{"d":"<p>Il servizio notifica al cittadino, tramite app IO, che è stato emesso un mandato di pagamento a suo favore.</p>\n","i":"01G3QYS71TKP4M0B8Z6Q8M5QN1","n":"Avviso di emissione mandato di pagamento","q":1,"sc":"LOCAL"},{"d":"<p>Il servizio notifica al dipendente dell’ente la presenza di documenti come cedolino e CU.</p>\n","i":"01G3QY8Y3PFNMPR2FA8PXRK8HZ","n":"Servizi per i dipendenti dell'Ente","q":1,"sc":"LOCAL"}],"prefix":null,"fn":"Acer Campania","st":"ACER CAMPANIA"}