{"o":"Comune di Civitella Messer Raimondo","fc":"81001410695","s":[{"i":"01EZF27TCSTAMS9Y1FKCPE195N","n":"Servizio Mensa Scolastica","d":"<p>Tramite IO potrai:</p>\n\n<ul>\n  <li>Ricevere notifiche</li>\n  <li>Effettuare il pagamento della Mensa Scolastica</li>\n  <li>Ricevere comunicazioni inerenti al servizio</li>\n</ul>\n","sc":"LOCAL","q":1},{"i":"01EZF2DADYPRPS7FTJVY7DVB44","n":"Servizio Trasporto Scolastico","d":"<p>Tramite IO potrai:</p>\n\n<ul>\n  <li>Ricevere notifiche</li>\n  <li>Effettuare il pagamento del Trasporto Scolastico</li>\n  <li>Ricevere comunicazioni inerenti al servizio</li>\n</ul>\n","sc":"LOCAL","q":1}],"prefix":"Comune di ","fn":"Civitella Messer Raimondo","st":"CIVITELLA MESSER RAIMONDO"}